{
    "data": [
        {
            "id": 1,
            "name": "Saurav Singh",
            "email": "saurav@gmail.com",
            "score": 78,
            "behavioural": 9,
            "communication": 8,
            "situation_handling": 6,
            "about": "Lorem ipsum dolor, sit amet consectetur adipisicing elit. Totam dolorem fugiat aut.",
            "experience": "Lorem ipsum dolor, sit amet consectetur adipisicing elit. Totam dolorem fugiat aut.",
            "hobbies": "Lorem ipsum dolor, sit amet consectetur adipisicing elit. Totam dolorem fugiat aut.",
            "introduction": "Lorem ipsum dolor, sit amet consectetur adipisicing elit. Totam dolorem fugiat aut.",
            "image":"https://images.unsplash.com/photo-1535713875002-d1d0cf377fde?q=80&w=1780&auto=format&fit=crop&ixlib=rb-4.0.3&ixid=M3wxMjA3fDB8MHxwaG90by1wYWdlfHx8fGVufDB8fHx8fA%3D%3D",
            "images": [
                {
                    "img": "https://images.unsplash.com/photo-1535713875002-d1d0cf377fde?q=80&w=1780&auto=format&fit=crop&ixlib=rb-4.0.3&ixid=M3wxMjA3fDB8MHxwaG90by1wYWdlfHx8fGVufDB8fHx8fA%3D%3D",
                    "question": "Tell me about yourself"
                },
                {
                    "img": "https://images.unsplash.com/photo-1535713875002-d1d0cf377fde?q=80&w=1780&auto=format&fit=crop&ixlib=rb-4.0.3&ixid=M3wxMjA3fDB8MHxwaG90by1wYWdlfHx8fGVufDB8fHx8fA%3D%3D",
                    "question": "Tell me about yourself"
                },
                {
                    "img": "https://images.unsplash.com/photo-1535713875002-d1d0cf377fde?q=80&w=1780&auto=format&fit=crop&ixlib=rb-4.0.3&ixid=M3wxMjA3fDB8MHxwaG90by1wYWdlfHx8fGVufDB8fHx8fA%3D%3D",
                    "question": "Tell me about yourself"
                },
                {
                    "img": "https://images.unsplash.com/photo-1535713875002-d1d0cf377fde?q=80&w=1780&auto=format&fit=crop&ixlib=rb-4.0.3&ixid=M3wxMjA3fDB8MHxwaG90by1wYWdlfHx8fGVufDB8fHx8fA%3D%3D",
                    "question": "Tell me about yourself"
                },
                {
                    "img": "https://images.unsplash.com/photo-1535713875002-d1d0cf377fde?q=80&w=1780&auto=format&fit=crop&ixlib=rb-4.0.3&ixid=M3wxMjA3fDB8MHxwaG90by1wYWdlfHx8fGVufDB8fHx8fA%3D%3D",
                    "question": "Tell me about yourself"
                },
                {
                    "img": "https://images.unsplash.com/photo-1535713875002-d1d0cf377fde?q=80&w=1780&auto=format&fit=crop&ixlib=rb-4.0.3&ixid=M3wxMjA3fDB8MHxwaG90by1wYWdlfHx8fGVufDB8fHx8fA%3D%3D",
                    "question": "Tell me about yourself"
                },
                {
                    "img": "https://images.unsplash.com/photo-1535713875002-d1d0cf377fde?q=80&w=1780&auto=format&fit=crop&ixlib=rb-4.0.3&ixid=M3wxMjA3fDB8MHxwaG90by1wYWdlfHx8fGVufDB8fHx8fA%3D%3D",
                    "question": "Tell me about yourself"
                },
                {
                    "img": "https://images.unsplash.com/photo-1535713875002-d1d0cf377fde?q=80&w=1780&auto=format&fit=crop&ixlib=rb-4.0.3&ixid=M3wxMjA3fDB8MHxwaG90by1wYWdlfHx8fGVufDB8fHx8fA%3D%3D",
                    "question": "Tell me about yourself"
                },
                {
                    "img": "https://images.unsplash.com/photo-1535713875002-d1d0cf377fde?q=80&w=1780&auto=format&fit=crop&ixlib=rb-4.0.3&ixid=M3wxMjA3fDB8MHxwaG90by1wYWdlfHx8fGVufDB8fHx8fA%3D%3D",
                    "question": "Tell me about yourself"
                },
                {
                    "img": "https://images.unsplash.com/photo-1535713875002-d1d0cf377fde?q=80&w=1780&auto=format&fit=crop&ixlib=rb-4.0.3&ixid=M3wxMjA3fDB8MHxwaG90by1wYWdlfHx8fGVufDB8fHx8fA%3D%3D",
                    "question": "Tell me about yourself"
                },
                {
                    "img": "https://images.unsplash.com/photo-1535713875002-d1d0cf377fde?q=80&w=1780&auto=format&fit=crop&ixlib=rb-4.0.3&ixid=M3wxMjA3fDB8MHxwaG90by1wYWdlfHx8fGVufDB8fHx8fA%3D%3D",
                    "question": "Tell me about yourself"
                }
            ]
        },
        {
            "id": 2,
            "name": "Emma Johnson",
            "email": "emma@gmail.com",
            "score": 67,
            "behavioural": 7,
            "communication": 7,
            "situation_handling": 6,
            "about": "Lorem ipsum dolor sit amet, consectetur adipiscing elit. Sed do eiusmod tempor incididunt ut labore et dolore magna aliqua.",
            "experience": "Lorem ipsum dolor sit amet, consectetur adipiscing elit. Ut enim ad minim veniam, quis nostrud exercitation ullamco laboris nisi ut aliquip ex ea commodo consequat.",
            "hobbies": "Lorem ipsum dolor sit amet, consectetur adipiscing elit. Duis aute irure dolor in reprehenderit in voluptate velit esse cillum dolore eu fugiat nulla pariatur.",
            "introduction": "Lorem ipsum dolor sit amet, consectetur adipiscing elit. Excepteur sint occaecat cupidatat non proident, sunt in culpa qui officia deserunt mollit anim id est laborum.",
            "image": "https://plus.unsplash.com/premium_photo-1688350808212-4e6908a03925?q=80&w=2069&auto=format&fit=crop&ixlib=rb-4.0.3&ixid=M3wxMjA3fDB8MHxwaG90by1wYWdlfHx8fGVufDB8fHx8fA%3D%3D",
            "images": [
                {
                    "img": "https://plus.unsplash.com/premium_photo-1688350808212-4e6908a03925?q=80&w=2069&auto=format&fit=crop&ixlib=rb-4.0.3&ixid=M3wxMjA3fDB8MHxwaG90by1wYWdlfHx8fGVufDB8fHx8fA%3D%3D",
                    "question": "Tell me about yourself"
                },
                {
                    "img": "https://plus.unsplash.com/premium_photo-1688350808212-4e6908a03925?q=80&w=2069&auto=format&fit=crop&ixlib=rb-4.0.3&ixid=M3wxMjA3fDB8MHxwaG90by1wYWdlfHx8fGVufDB8fHx8fA%3D%3D",
                    "question": "Tell me about yourself"
                },
                {
                    "img": "https://plus.unsplash.com/premium_photo-1688350808212-4e6908a03925?q=80&w=2069&auto=format&fit=crop&ixlib=rb-4.0.3&ixid=M3wxMjA3fDB8MHxwaG90by1wYWdlfHx8fGVufDB8fHx8fA%3D%3D",
                    "question": "Tell me about yourself"
                },
                {
                    "img": "https://plus.unsplash.com/premium_photo-1688350808212-4e6908a03925?q=80&w=2069&auto=format&fit=crop&ixlib=rb-4.0.3&ixid=M3wxMjA3fDB8MHxwaG90by1wYWdlfHx8fGVufDB8fHx8fA%3D%3D",
                    "question": "Tell me about yourself"
                },
                {
                    "img": "https://plus.unsplash.com/premium_photo-1688350808212-4e6908a03925?q=80&w=2069&auto=format&fit=crop&ixlib=rb-4.0.3&ixid=M3wxMjA3fDB8MHxwaG90by1wYWdlfHx8fGVufDB8fHx8fA%3D%3D",
                    "question": "Tell me about yourself"
                },
                {
                    "img": "https://plus.unsplash.com/premium_photo-1688350808212-4e6908a03925?q=80&w=2069&auto=format&fit=crop&ixlib=rb-4.0.3&ixid=M3wxMjA3fDB8MHxwaG90by1wYWdlfHx8fGVufDB8fHx8fA%3D%3D",
                    "question": "Tell me about yourself"
                },
                {
                    "img": "https://plus.unsplash.com/premium_photo-1688350808212-4e6908a03925?q=80&w=2069&auto=format&fit=crop&ixlib=rb-4.0.3&ixid=M3wxMjA3fDB8MHxwaG90by1wYWdlfHx8fGVufDB8fHx8fA%3D%3D",
                    "question": "Tell me about yourself"
                },
                {
                    "img": "https://plus.unsplash.com/premium_photo-1688350808212-4e6908a03925?q=80&w=2069&auto=format&fit=crop&ixlib=rb-4.0.3&ixid=M3wxMjA3fDB8MHxwaG90by1wYWdlfHx8fGVufDB8fHx8fA%3D%3D",
                    "question": "Tell me about yourself"
                },
                {
                    "img": "https://plus.unsplash.com/premium_photo-1688350808212-4e6908a03925?q=80&w=2069&auto=format&fit=crop&ixlib=rb-4.0.3&ixid=M3wxMjA3fDB8MHxwaG90by1wYWdlfHx8fGVufDB8fHx8fA%3D%3D",
                    "question": "Tell me about yourself"
                },
                {
                    "img": "https://plus.unsplash.com/premium_photo-1688350808212-4e6908a03925?q=80&w=2069&auto=format&fit=crop&ixlib=rb-4.0.3&ixid=M3wxMjA3fDB8MHxwaG90by1wYWdlfHx8fGVufDB8fHx8fA%3D%3D",
                    "question": "Tell me about yourself"
                },
                {
                    "img": "https://plus.unsplash.com/premium_photo-1688350808212-4e6908a03925?q=80&w=2069&auto=format&fit=crop&ixlib=rb-4.0.3&ixid=M3wxMjA3fDB8MHxwaG90by1wYWdlfHx8fGVufDB8fHx8fA%3D%3D",
                    "question": "Tell me about yourself"
                }
            ]
        },
        {
            "id": 3,
            "name": "Michael Smith",
            "email": "michael@gmail.com",
            "score": 92,
            "behavioural": 9,
            "communication": 8,
            "situation_handling": 9,
            "about": "Lorem ipsum dolor sit amet, consectetur adipiscing elit. Sed ut perspiciatis unde omnis iste natus error sit voluptatem accusantium doloremque laudantium.",
            "experience": "Lorem ipsum dolor sit amet, consectetur adipiscing elit. Totam rem aperiam, eaque ipsa quae ab illo inventore veritatis et quasi architecto beatae vitae dicta sunt explicabo.",
            "hobbies": "Lorem ipsum dolor sit amet, consectetur adipiscing elit. Nemo enim ipsam voluptatem quia voluptas sit aspernatur aut odit aut fugit.",
            "introduction": "Lorem ipsum dolor sit amet, consectetur adipiscing elit. Neque porro quisquam est, qui dolorem ipsum quia dolor sit amet, consectetur, adipisci velit.",
            "image": "https://images.unsplash.com/photo-1560250097-0b93528c311a?q=80&w=1887&auto=format&fit=crop&ixlib=rb-4.0.3&ixid=M3wxMjA3fDB8MHxwaG90by1wYWdlfHx8fGVufDB8fHx8fA%3D%3D",
            "images": [
                {
                    "img": "https://images.unsplash.com/photo-1560250097-0b93528c311a?q=80&w=1887&auto=format&fit=crop&ixlib=rb-4.0.3&ixid=M3wxMjA3fDB8MHxwaG90by1wYWdlfHx8fGVufDB8fHx8fA%3D%3D",
                    "question": "Tell me about yourself"
                },
                {
                    "img": "https://images.unsplash.com/photo-1560250097-0b93528c311a?q=80&w=1887&auto=format&fit=crop&ixlib=rb-4.0.3&ixid=M3wxMjA3fDB8MHxwaG90by1wYWdlfHx8fGVufDB8fHx8fA%3D%3D",
                    "question": "Tell me about yourself"
                },
                {
                    "img": "https://images.unsplash.com/photo-1560250097-0b93528c311a?q=80&w=1887&auto=format&fit=crop&ixlib=rb-4.0.3&ixid=M3wxMjA3fDB8MHxwaG90by1wYWdlfHx8fGVufDB8fHx8fA%3D%3D",
                    "question": "Tell me about yourself"
                },
                {
                    "img": "https://images.unsplash.com/photo-1560250097-0b93528c311a?q=80&w=1887&auto=format&fit=crop&ixlib=rb-4.0.3&ixid=M3wxMjA3fDB8MHxwaG90by1wYWdlfHx8fGVufDB8fHx8fA%3D%3D",
                    "question": "Tell me about yourself"
                },
                {
                    "img": "https://images.unsplash.com/photo-1560250097-0b93528c311a?q=80&w=1887&auto=format&fit=crop&ixlib=rb-4.0.3&ixid=M3wxMjA3fDB8MHxwaG90by1wYWdlfHx8fGVufDB8fHx8fA%3D%3D",
                    "question": "Tell me about yourself"
                },
                {
                    "img": "https://images.unsplash.com/photo-1560250097-0b93528c311a?q=80&w=1887&auto=format&fit=crop&ixlib=rb-4.0.3&ixid=M3wxMjA3fDB8MHxwaG90by1wYWdlfHx8fGVufDB8fHx8fA%3D%3D",
                    "question": "Tell me about yourself"
                },
                {
                    "img": "https://images.unsplash.com/photo-1560250097-0b93528c311a?q=80&w=1887&auto=format&fit=crop&ixlib=rb-4.0.3&ixid=M3wxMjA3fDB8MHxwaG90by1wYWdlfHx8fGVufDB8fHx8fA%3D%3D",
                    "question": "Tell me about yourself"
                },
                {
                    "img": "https://images.unsplash.com/photo-1560250097-0b93528c311a?q=80&w=1887&auto=format&fit=crop&ixlib=rb-4.0.3&ixid=M3wxMjA3fDB8MHxwaG90by1wYWdlfHx8fGVufDB8fHx8fA%3D%3D",
                    "question": "Tell me about yourself"
                },
                {
                    "img": "https://images.unsplash.com/photo-1560250097-0b93528c311a?q=80&w=1887&auto=format&fit=crop&ixlib=rb-4.0.3&ixid=M3wxMjA3fDB8MHxwaG90by1wYWdlfHx8fGVufDB8fHx8fA%3D%3D",
                    "question": "Tell me about yourself"
                },
                {
                    "img": "https://images.unsplash.com/photo-1560250097-0b93528c311a?q=80&w=1887&auto=format&fit=crop&ixlib=rb-4.0.3&ixid=M3wxMjA3fDB8MHxwaG90by1wYWdlfHx8fGVufDB8fHx8fA%3D%3D",
                    "question": "Tell me about yourself"
                }
            ]
        },
        {
            "id": 4,
            "name": "Sophia Brown",
            "email": "sophia@gmail.com",
            "score": 34,
            "behavioural": 7,
            "communication": 6,
            "situation_handling": 5,
            "about": "Lorem ipsum dolor sit amet, consectetur adipiscing elit. At vero eos et accusamus et iusto odio dignissimos ducimus qui blanditiis praesentium voluptatum deleniti atque corrupti quos dolores et quas molestias excepturi sint occaecati cupiditate non provident.",
            "experience": "Lorem ipsum dolor sit amet, consectetur adipiscing elit. Similique sunt in culpa qui officia deserunt mollitia animi, id est laborum et dolorum fuga.",
            "hobbies": "Lorem ipsum dolor sit amet, consectetur adipiscing elit. Et harum quidem rerum facilis est et expedita distinctio.",
            "introduction": "Lorem ipsum dolor sit amet, consectetur adipiscing elit. Nam libero tempore, cum soluta nobis est eligendi optio cumque nihil impedit quo minus id quod maxime placeat facere possimus, omnis voluptas assumenda est, omnis dolor repellendus.",
            "image": "https://images.unsplash.com/photo-1619895862022-09114b41f16f?q=80&w=2070&auto=format&fit=crop&ixlib=rb-4.0.3&ixid=M3wxMjA3fDB8MHxwaG90by1wYWdlfHx8fGVufDB8fHx8fA%3D%3D",
            "images": [
                {
                    "img": "https://images.unsplash.com/photo-1619895862022-09114b41f16f?q=80&w=2070&auto=format&fit=crop&ixlib=rb-4.0.3&ixid=M3wxMjA3fDB8MHxwaG90by1wYWdlfHx8fGVufDB8fHx8fA%3D%3D",
                    "question": "Tell me about yourself"
                },
                {
                    "img": "https://images.unsplash.com/photo-1619895862022-09114b41f16f?q=80&w=2070&auto=format&fit=crop&ixlib=rb-4.0.3&ixid=M3wxMjA3fDB8MHxwaG90by1wYWdlfHx8fGVufDB8fHx8fA%3D%3D",
                    "question": "Tell me about yourself"
                },
                {
                    "img": "https://images.unsplash.com/photo-1619895862022-09114b41f16f?q=80&w=2070&auto=format&fit=crop&ixlib=rb-4.0.3&ixid=M3wxMjA3fDB8MHxwaG90by1wYWdlfHx8fGVufDB8fHx8fA%3D%3D",
                    "question": "Tell me about yourself"
                },
                {
                    "img": "https://images.unsplash.com/photo-1619895862022-09114b41f16f?q=80&w=2070&auto=format&fit=crop&ixlib=rb-4.0.3&ixid=M3wxMjA3fDB8MHxwaG90by1wYWdlfHx8fGVufDB8fHx8fA%3D%3D",
                    "question": "Tell me about yourself"
                },
                {
                    "img": "https://images.unsplash.com/photo-1619895862022-09114b41f16f?q=80&w=2070&auto=format&fit=crop&ixlib=rb-4.0.3&ixid=M3wxMjA3fDB8MHxwaG90by1wYWdlfHx8fGVufDB8fHx8fA%3D%3D",
                    "question": "Tell me about yourself"
                },
                {
                    "img": "https://images.unsplash.com/photo-1619895862022-09114b41f16f?q=80&w=2070&auto=format&fit=crop&ixlib=rb-4.0.3&ixid=M3wxMjA3fDB8MHxwaG90by1wYWdlfHx8fGVufDB8fHx8fA%3D%3D",
                    "question": "Tell me about yourself"
                },
                {
                    "img": "https://images.unsplash.com/photo-1619895862022-09114b41f16f?q=80&w=2070&auto=format&fit=crop&ixlib=rb-4.0.3&ixid=M3wxMjA3fDB8MHxwaG90by1wYWdlfHx8fGVufDB8fHx8fA%3D%3D",
                    "question": "Tell me about yourself"
                },
                {
                    "img": "https://images.unsplash.com/photo-1619895862022-09114b41f16f?q=80&w=2070&auto=format&fit=crop&ixlib=rb-4.0.3&ixid=M3wxMjA3fDB8MHxwaG90by1wYWdlfHx8fGVufDB8fHx8fA%3D%3D",
                    "question": "Tell me about yourself"
                },
                {
                    "img": "https://images.unsplash.com/photo-1619895862022-09114b41f16f?q=80&w=2070&auto=format&fit=crop&ixlib=rb-4.0.3&ixid=M3wxMjA3fDB8MHxwaG90by1wYWdlfHx8fGVufDB8fHx8fA%3D%3D",
                    "question": "Tell me about yourself"
                },
                {
                    "img": "https://images.unsplash.com/photo-1619895862022-09114b41f16f?q=80&w=2070&auto=format&fit=crop&ixlib=rb-4.0.3&ixid=M3wxMjA3fDB8MHxwaG90by1wYWdlfHx8fGVufDB8fHx8fA%3D%3D",
                    "question": "Tell me about yourself"
                },
                {
                    "img": "https://images.unsplash.com/photo-1619895862022-09114b41f16f?q=80&w=2070&auto=format&fit=crop&ixlib=rb-4.0.3&ixid=M3wxMjA3fDB8MHxwaG90by1wYWdlfHx8fGVufDB8fHx8fA%3D%3D",
                    "question": "Tell me about yourself"
                }
            ]
        },
        {
            "id": 5,
            "name": "Liam Wilson",
            "email": "liam@gmail.com",
            "score": 88,
            "behavioural": 9,
            "communication": 9,
            "situation_handling": 8,
            "about": "Lorem ipsum dolor sit amet, consectetur adipiscing elit. Ut enim ad minima veniam, quis nostrum exercitationem ullam corporis suscipit laboriosam.",
            "experience": "Lorem ipsum dolor sit amet, consectetur adipiscing elit. Quis autem vel eum iure reprehenderit qui in ea voluptate velit esse quam nihil molestiae consequatur.",
            "hobbies": "Lorem ipsum dolor sit amet, consectetur adipiscing elit. Vel illum qui dolorem eum fugiat quo voluptas nulla pariatur?",
            "introduction": "Lorem ipsum dolor sit amet, consectetur adipiscing elit. At vero eos et accusamus et iusto odio dignissimos ducimus qui blanditiis praesentium voluptatum deleniti atque corrupti quos dolores et quas molestias excepturi sint occaecati cupiditate non provident.",
            "image": "https://images.unsplash.com/photo-1629425733761-caae3b5f2e50?q=80&w=1887&auto=format&fit=crop&ixlib=rb-4.0.3&ixid=M3wxMjA3fDB8MHxwaG90by1wYWdlfHx8fGVufDB8fHx8fA%3D%3D",
            "images": [
                {
                    "img": "https://images.unsplash.com/photo-1629425733761-caae3b5f2e50?q=80&w=1887&auto=format&fit=crop&ixlib=rb-4.0.3&ixid=M3wxMjA3fDB8MHxwaG90by1wYWdlfHx8fGVufDB8fHx8fA%3D%3D",
                    "question": "Tell me about yourself"
                },
                {
                    "img": "https://images.unsplash.com/photo-1629425733761-caae3b5f2e50?q=80&w=1887&auto=format&fit=crop&ixlib=rb-4.0.3&ixid=M3wxMjA3fDB8MHxwaG90by1wYWdlfHx8fGVufDB8fHx8fA%3D%3D",
                    "question": "Tell me about yourself"
                },
                {
                    "img": "https://images.unsplash.com/photo-1629425733761-caae3b5f2e50?q=80&w=1887&auto=format&fit=crop&ixlib=rb-4.0.3&ixid=M3wxMjA3fDB8MHxwaG90by1wYWdlfHx8fGVufDB8fHx8fA%3D%3D",
                    "question": "Tell me about yourself"
                },
                {
                    "img": "https://images.unsplash.com/photo-1629425733761-caae3b5f2e50?q=80&w=1887&auto=format&fit=crop&ixlib=rb-4.0.3&ixid=M3wxMjA3fDB8MHxwaG90by1wYWdlfHx8fGVufDB8fHx8fA%3D%3D",
                    "question": "Tell me about yourself"
                },
                {
                    "img": "https://images.unsplash.com/photo-1629425733761-caae3b5f2e50?q=80&w=1887&auto=format&fit=crop&ixlib=rb-4.0.3&ixid=M3wxMjA3fDB8MHxwaG90by1wYWdlfHx8fGVufDB8fHx8fA%3D%3D",
                    "question": "Tell me about yourself"
                },
                {
                    "img": "https://images.unsplash.com/photo-1629425733761-caae3b5f2e50?q=80&w=1887&auto=format&fit=crop&ixlib=rb-4.0.3&ixid=M3wxMjA3fDB8MHxwaG90by1wYWdlfHx8fGVufDB8fHx8fA%3D%3D",
                    "question": "Tell me about yourself"
                },
                {
                    "img": "https://images.unsplash.com/photo-1629425733761-caae3b5f2e50?q=80&w=1887&auto=format&fit=crop&ixlib=rb-4.0.3&ixid=M3wxMjA3fDB8MHxwaG90by1wYWdlfHx8fGVufDB8fHx8fA%3D%3D",
                    "question": "Tell me about yourself"
                },
                {
                    "img": "https://images.unsplash.com/photo-1629425733761-caae3b5f2e50?q=80&w=1887&auto=format&fit=crop&ixlib=rb-4.0.3&ixid=M3wxMjA3fDB8MHxwaG90by1wYWdlfHx8fGVufDB8fHx8fA%3D%3D",
                    "question": "Tell me about yourself"
                },
                {
                    "img": "https://images.unsplash.com/photo-1629425733761-caae3b5f2e50?q=80&w=1887&auto=format&fit=crop&ixlib=rb-4.0.3&ixid=M3wxMjA3fDB8MHxwaG90by1wYWdlfHx8fGVufDB8fHx8fA%3D%3D",
                    "question": "Tell me about yourself"
                },
                {
                    "img": "https://images.unsplash.com/photo-1629425733761-caae3b5f2e50?q=80&w=1887&auto=format&fit=crop&ixlib=rb-4.0.3&ixid=M3wxMjA3fDB8MHxwaG90by1wYWdlfHx8fGVufDB8fHx8fA%3D%3D",
                    "question": "Tell me about yourself"
                },
                {
                    "img": "https://images.unsplash.com/photo-1629425733761-caae3b5f2e50?q=80&w=1887&auto=format&fit=crop&ixlib=rb-4.0.3&ixid=M3wxMjA3fDB8MHxwaG90by1wYWdlfHx8fGVufDB8fHx8fA%3D%3D",
                    "question": "Tell me about yourself"
                }
            ]
        },
        {
            "id": 6,
            "name": "Olivia Garcia",
            "email": "olivia@gmail.com",
            "score": 45,
            "behavioural": 8,
            "communication": 5,
            "situation_handling": 9,
            "about": "Lorem ipsum dolor sit amet, consectetur adipiscing elit. Sed quia non numquam eius modi tempora incidunt ut labore et dolore magnam aliquam quaerat voluptatem.",
            "experience": "Lorem ipsum dolor sit amet, consectetur adipiscing elit. Ut enim ad minima veniam, quis nostrum exercitationem ullam corporis suscipit laboriosam.",
            "hobbies": "Lorem ipsum dolor sit amet, consectetur adipiscing elit. Neque porro quisquam est, qui dolorem ipsum quia dolor sit amet, consectetur, adipisci velit.",
            "introduction": "Lorem ipsum dolor sit amet, consectetur adipiscing elit. Duis aute irure dolor in reprehenderit in voluptate velit esse cillum dolore eu fugiat nulla pariatur.",
            "image":"https://images.unsplash.com/photo-1573497019236-17f8177b81e8?q=80&w=2070&auto=format&fit=crop&ixlib=rb-4.0.3&ixid=M3wxMjA3fDB8MHxwaG90by1wYWdlfHx8fGVufDB8fHx8fA%3D%3D",
            "images":[
                {
                    "img":"https://images.unsplash.com/photo-1573497019236-17f8177b81e8?q=80&w=2070&auto=format&fit=crop&ixlib=rb-4.0.3&ixid=M3wxMjA3fDB8MHxwaG90by1wYWdlfHx8fGVufDB8fHx8fA%3D%3D",
                    "question":"Tell me about yourself"
                },
                {
                    "img":"https://images.unsplash.com/photo-1573497019236-17f8177b81e8?q=80&w=2070&auto=format&fit=crop&ixlib=rb-4.0.3&ixid=M3wxMjA3fDB8MHxwaG90by1wYWdlfHx8fGVufDB8fHx8fA%3D%3D",
                    "question":"Tell me about yourself"
                },
                {
                    "img":"https://images.unsplash.com/photo-1573497019236-17f8177b81e8?q=80&w=2070&auto=format&fit=crop&ixlib=rb-4.0.3&ixid=M3wxMjA3fDB8MHxwaG90by1wYWdlfHx8fGVufDB8fHx8fA%3D%3D",
                    "question":"Tell me about yourself"
                },
                {
                    "img":"https://images.unsplash.com/photo-1573497019236-17f8177b81e8?q=80&w=2070&auto=format&fit=crop&ixlib=rb-4.0.3&ixid=M3wxMjA3fDB8MHxwaG90by1wYWdlfHx8fGVufDB8fHx8fA%3D%3D",
                    "question":"Tell me about yourself"
                },
                {
                    "img":"https://images.unsplash.com/photo-1573497019236-17f8177b81e8?q=80&w=2070&auto=format&fit=crop&ixlib=rb-4.0.3&ixid=M3wxMjA3fDB8MHxwaG90by1wYWdlfHx8fGVufDB8fHx8fA%3D%3D",
                    "question":"Tell me about yourself"
                },
                {
                    "img":"https://images.unsplash.com/photo-1573497019236-17f8177b81e8?q=80&w=2070&auto=format&fit=crop&ixlib=rb-4.0.3&ixid=M3wxMjA3fDB8MHxwaG90by1wYWdlfHx8fGVufDB8fHx8fA%3D%3D",
                    "question":"Tell me about yourself"
                },
                {
                    "img":"https://images.unsplash.com/photo-1573497019236-17f8177b81e8?q=80&w=2070&auto=format&fit=crop&ixlib=rb-4.0.3&ixid=M3wxMjA3fDB8MHxwaG90by1wYWdlfHx8fGVufDB8fHx8fA%3D%3D",
                    "question":"Tell me about yourself"
                },
                {
                    "img":"https://images.unsplash.com/photo-1573497019236-17f8177b81e8?q=80&w=2070&auto=format&fit=crop&ixlib=rb-4.0.3&ixid=M3wxMjA3fDB8MHxwaG90by1wYWdlfHx8fGVufDB8fHx8fA%3D%3D",
                    "question":"Tell me about yourself"
                },
                {
                    "img":"https://images.unsplash.com/photo-1573497019236-17f8177b81e8?q=80&w=2070&auto=format&fit=crop&ixlib=rb-4.0.3&ixid=M3wxMjA3fDB8MHxwaG90by1wYWdlfHx8fGVufDB8fHx8fA%3D%3D",
                    "question":"Tell me about yourself"
                },
                {
                    "img":"https://images.unsplash.com/photo-1573497019236-17f8177b81e8?q=80&w=2070&auto=format&fit=crop&ixlib=rb-4.0.3&ixid=M3wxMjA3fDB8MHxwaG90by1wYWdlfHx8fGVufDB8fHx8fA%3D%3D",
                    "question":"Tell me about yourself"
                },
                {
                    "img":"https://images.unsplash.com/photo-1573497019236-17f8177b81e8?q=80&w=2070&auto=format&fit=crop&ixlib=rb-4.0.3&ixid=M3wxMjA3fDB8MHxwaG90by1wYWdlfHx8fGVufDB8fHx8fA%3D%3D",
                    "question":"Tell me about yourself"
                }
            ] 
        }
    ]
}